minecraft_ping_urpagin/__init__.py
minecraft_ping_urpagin/minecraft_ping.py
minecraft_ping_urpagin-0.0.1.dist-info/METADATA
minecraft_ping_urpagin-0.0.1.dist-info/WHEEL
minecraft_ping_urpagin-0.0.1.dist-info/licenses/LICENSE
minecraft_ping_urpagin-0.0.1.dist-info/RECORD
