Metadata-Version: 2.3
Name: minecraft_ping_urpagin
Version: 0.0.1
Summary: Pings minecraft server to get their online/offline state. Offers bulk async pinging.
Project-URL: Homepage, https://github.com/Urpagin/sampleproject
Author-email: Urpagin <urpagin@proton.me>
License-File: LICENSE
Classifier: License :: OSI Approved :: MIT License
Classifier: Operating System :: OS Independent
Classifier: Programming Language :: Python :: 3
Requires-Python: >=3.10
